{
    "initialization": {
        "components": {
            "CO2": {
                "acentricFactor": 0.225,
                "bondTypes": [],
                "cbmcStartingBead": 0,
                "criticalPressure": 7380000.0,
                "criticalTemperature": 304.1,
                "diagonalizedInertiaVector": [
                    42.2448477588,
                    42.2448477588,
                    0.0
                ],
                "mass": 44.0095,
                "molFraction": 1.0,
                "moveProbabilities": [
                    0.0,
                    0.0,
                    0.0,
                    0.0,
                    0.0,
                    0.0,
                    0.0,
                    0.0,
                    0.0,
                    0.0,
                    0.0,
                    0.0,
                    0.0,
                    0.0,
                    0.0,
                    1.0,
                    0.0,
                    0.0,
                    0.0,
                    0.0
                ],
                "n_atoms": 3,
                "n_bonds": 0,
                "name": "CO2",
                "netCharge": 0.0,
                "rotationalDOF": 2,
                "shape": "linear",
                "swappable": false,
                "translationalDOF": 3
            },
            "Na-Rho_CO2_open_0p1bar": {
                "bondTypes": [],
                "id": 0,
                "mass": 26326.803200000453,
                "n_bonds": 0,
                "name": "Na-Rho_CO2_open_0p1bar"
            }
        },
        "forceField": {
            "Ewald": {
                "alpha": 0.26505830360350674,
                "kVectors": [
                    8,
                    8,
                    8
                ],
                "precision": 1e-06
            },
            "interactions": [
                {
                    "potential": "Lennard-Jones",
                    "shift [K]": -0.004362552641146898,
                    "tailCorrections": false,
                    "typeA": "Al",
                    "typeB": "Al",
                    "ε/kʙ [K]": 22.0,
                    "σ/kʙ [Å]": 2.3
                },
                {
                    "potential": "Lennard-Jones",
                    "shift [K]": -0.005662896354727172,
                    "tailCorrections": false,
                    "typeA": "Al",
                    "typeB": "Na",
                    "ε/kʙ [K]": 18.224302455786887,
                    "σ/kʙ [Å]": 2.4787999999999997
                },
                {
                    "potential": "Lennard-Jones",
                    "shift [K]": -0.0220394059533039,
                    "tailCorrections": false,
                    "typeA": "Al",
                    "typeB": "O",
                    "ε/kʙ [K]": 34.14674215792774,
                    "σ/kʙ [Å]": 2.8
                },
                {
                    "potential": "Lennard-Jones",
                    "shift [K]": -0.004362552641146898,
                    "tailCorrections": false,
                    "typeA": "Al",
                    "typeB": "Si",
                    "ε/kʙ [K]": 22.0,
                    "σ/kʙ [Å]": 2.3
                },
                {
                    "potential": "Lennard-Jones",
                    "shift [K]": -0.008738682970271137,
                    "tailCorrections": false,
                    "typeA": "Al",
                    "typeB": "C_co2",
                    "ε/kʙ [K]": 24.876454731331794,
                    "σ/kʙ [Å]": 2.53
                },
                {
                    "potential": "Lennard-Jones",
                    "shift [K]": -0.020262728289572464,
                    "tailCorrections": false,
                    "typeA": "Al",
                    "typeB": "O_co2",
                    "ε/kʙ [K]": 42.08508049178474,
                    "σ/kʙ [Å]": 2.6665
                },
                {
                    "potential": "Lennard-Jones",
                    "shift [K]": -0.007124232885862057,
                    "tailCorrections": false,
                    "typeA": "Na",
                    "typeB": "Na",
                    "ε/kʙ [K]": 15.0966,
                    "σ/kʙ [Å]": 2.6576
                },
                {
                    "potential": "Lennard-Jones",
                    "shift [K]": -0.02646649745368645,
                    "tailCorrections": false,
                    "typeA": "Na",
                    "typeB": "O",
                    "ε/kʙ [K]": 28.286388952992922,
                    "σ/kʙ [Å]": 2.9787999999999997
                },
                {
                    "potential": "Lennard-Jones",
                    "shift [K]": -0.005662896354727172,
                    "tailCorrections": false,
                    "typeA": "Na",
                    "typeB": "Si",
                    "ε/kʙ [K]": 18.224302455786887,
                    "σ/kʙ [Å]": 2.4787999999999997
                },
                {
                    "potential": "Lennard-Jones",
                    "shift [K]": -0.6496283154671694,
                    "tailCorrections": false,
                    "typeA": "Na",
                    "typeB": "C_co2",
                    "ε/kʙ [K]": 362.2919999999999,
                    "σ/kʙ [Å]": 3.32
                },
                {
                    "potential": "Lennard-Jones",
                    "shift [K]": -0.11838721931983155,
                    "tailCorrections": false,
                    "typeA": "Na",
                    "typeB": "O_co2",
                    "ε/kʙ [K]": 200.831,
                    "σ/kʙ [Å]": 2.758
                },
                {
                    "potential": "Lennard-Jones",
                    "shift [K]": -0.09165246430970037,
                    "tailCorrections": false,
                    "typeA": "O",
                    "typeB": "O",
                    "ε/kʙ [K]": 52.99999999999999,
                    "σ/kʙ [Å]": 3.3
                },
                {
                    "potential": "Lennard-Jones",
                    "shift [K]": -0.0220394059533039,
                    "tailCorrections": false,
                    "typeA": "O",
                    "typeB": "Si",
                    "ε/kʙ [K]": 34.14674215792774,
                    "σ/kʙ [Å]": 2.8
                },
                {
                    "potential": "Lennard-Jones",
                    "shift [K]": -0.09427901763705203,
                    "tailCorrections": false,
                    "typeA": "O",
                    "typeB": "C_co2",
                    "ε/kʙ [K]": 37.595,
                    "σ/kʙ [Å]": 3.511
                },
                {
                    "potential": "Lennard-Jones",
                    "shift [K]": -0.12166859322698428,
                    "tailCorrections": false,
                    "typeA": "O",
                    "typeB": "O_co2",
                    "ε/kʙ [K]": 78.97999999999999,
                    "σ/kʙ [Å]": 3.237
                },
                {
                    "potential": "Lennard-Jones",
                    "shift [K]": -0.004362552641146898,
                    "tailCorrections": false,
                    "typeA": "Si",
                    "typeB": "Si",
                    "ε/kʙ [K]": 22.0,
                    "σ/kʙ [Å]": 2.3
                },
                {
                    "potential": "Lennard-Jones",
                    "shift [K]": -0.008738682970271137,
                    "tailCorrections": false,
                    "typeA": "Si",
                    "typeB": "C_co2",
                    "ε/kʙ [K]": 24.876454731331794,
                    "σ/kʙ [Å]": 2.53
                },
                {
                    "potential": "Lennard-Jones",
                    "shift [K]": -0.020262728289572464,
                    "tailCorrections": false,
                    "typeA": "Si",
                    "typeB": "O_co2",
                    "ε/kʙ [K]": 42.08508049178474,
                    "σ/kʙ [Å]": 2.6665
                },
                {
                    "potential": "Lennard-Jones",
                    "shift [K]": -0.0166539403408414,
                    "tailCorrections": false,
                    "typeA": "C_co2",
                    "typeB": "C_co2",
                    "ε/kʙ [K]": 28.129,
                    "σ/kʙ [Å]": 2.76
                },
                {
                    "potential": "Lennard-Jones",
                    "shift [K]": -0.037637587894305116,
                    "tailCorrections": false,
                    "typeA": "C_co2",
                    "typeB": "O_co2",
                    "ε/kʙ [K]": 47.58761816901535,
                    "σ/kʙ [Å]": 2.8964999999999996
                },
                {
                    "potential": "Lennard-Jones",
                    "shift [K]": -0.08393196357541287,
                    "tailCorrections": false,
                    "typeA": "O_co2",
                    "typeB": "O_co2",
                    "ε/kʙ [K]": 80.507,
                    "σ/kʙ [Å]": 3.033
                }
            ],
            "pseudoAtoms": [
                {
                    "charge": 1.111224489795917,
                    "mass": 26.9815,
                    "name": "Al",
                    "source": "Lozinska_2012_composition_electroneutrality"
                },
                {
                    "charge": 1.0,
                    "mass": 22.9898,
                    "name": "Na",
                    "source": "UFF cation fallback"
                },
                {
                    "charge": -1.025,
                    "mass": 15.9994,
                    "name": "O",
                    "source": "Jaramillo-Auerbach 1999 via García-Pérez 2007"
                },
                {
                    "charge": 2.05,
                    "mass": 28.0855,
                    "name": "Si",
                    "source": "Jaramillo-Auerbach 1999 via García-Pérez 2007"
                },
                {
                    "charge": 0.6512,
                    "mass": 12.0107,
                    "name": "C_co2",
                    "source": "Harris-Yung 1995 CO2"
                },
                {
                    "charge": -0.3256,
                    "mass": 15.9994,
                    "name": "O_co2",
                    "source": "Harris-Yung 1995 CO2"
                }
            ]
        },
        "hardwareInfo": {
            "compile_date": "May  8 2026",
            "compile_time": "02:11:23",
            "compiler": "gcc Clang 19.1.7 (https://github.com/conda-forge/clangdev-feedstock 3c5e7de432e909e225d8040e72a44724afb0c446)",
            "hostname": "wselimited-3",
            "os_arch": "x86_64",
            "os_release": "6.8.0-111-generic",
            "os_type": "Linux",
            "os_version": "#111~22.04.1-Ubuntu SMP PREEMPT_DYNAMIC Tue Apr 14 17:13:45 UTC ",
            "start_date": "Sun, May 17",
            "start_time": "14:29:00"
        },
        "initialConditions": {
            "beta": 0.004035983951527738,
            "box": [
                [
                    29.25646,
                    0.0,
                    0.0
                ],
                [
                    1.7914415046691288e-15,
                    29.25646,
                    0.0
                ],
                [
                    1.7914415046691288e-15,
                    1.7914415046691288e-15,
                    29.25646
                ]
            ],
            "boxAngles": [
                90.0,
                90.0,
                90.0
            ],
            "boxLengths": [
                29.25646,
                29.25646,
                29.25646
            ],
            "pressure": 0.0,
            "temperature": 298.0
        },
        "reactions": null,
        "units": {
            "Boltzmann constant [-]": 0.8314464919307584,
            "Coulomb potential [K]": 167101.08000665612,
            "Energy to Kelvin [-]": 1.202724284692786,
            "Kelvin to energy [-]": 0.8314457542157567,
            "acceleration [m²/s]": 1e-08,
            "charge [C/particle]": 1.60217733e-19,
            "dielectric constant [s² C²/(kg m³)]": 1.5458657349975193e-05,
            "diffusion [m²/s]": 1e-08,
            "dipole moment [C.m]": 1.60217733e-29,
            "electric field [V]": 1036427.222447343,
            "electric potential [V]": 0.00010364272224473431,
            "energy [J]": 1.6605402000000002e-23,
            "force [N]": 1.6605402000000002e-13,
            "length [m]": 1e-10,
            "mass [kg]": 1.6605402e-27,
            "polarizability [-]": 1.5458657349975198e-35,
            "pressure [Pa]": 16605402.0,
            "temperature": "Kelvin",
            "time [s]": 1e-12,
            "velocity [m/s]": 100.0
        }
    },
    "output": {
        "MCMoveStatistics": {
            "system": {
                "CO2": {
                    "Gibbs swap (CBMC)": {
                        "accepted": 0.0,
                        "all": 0,
                        "constructed": 0.0,
                        "fraction": 0.0,
                        "maxChange": 0.0,
                        "total": 0.0
                    },
                    "Gibbs swap (CFCMC)": {
                        "accepted": [
                            0.0,
                            0.0,
                            0.0
                        ],
                        "all": 0,
                        "constructed": [
                            0.0,
                            0.0,
                            0.0
                        ],
                        "fraction": [
                            0.0,
                            0.0,
                            0.0
                        ],
                        "maxChange": [
                            0.0,
                            0.0,
                            0.5
                        ],
                        "total": [
                            0.0,
                            0.0,
                            0.0
                        ]
                    },
                    "Gibbs volume": {
                        "accepted": 0.0,
                        "all": 0,
                        "constructed": 0.0,
                        "fraction": 0.0,
                        "maxChange": 0.1,
                        "total": 0.0
                    },
                    "Hybrid MC": {
                        "accepted": 0.0,
                        "all": 0,
                        "constructed": 0.0,
                        "fraction": 0.0,
                        "maxChange": 0.0005,
                        "total": 0.0
                    },
                    "Identity change (CBMC)": {
                        "accepted": 0.0,
                        "all": 0,
                        "constructed": 0.0,
                        "fraction": 0.0,
                        "maxChange": 0.0,
                        "total": 0.0
                    },
                    "Parallel tempering": {
                        "accepted": 0.0,
                        "all": 0,
                        "constructed": 0.0,
                        "fraction": 0.0,
                        "maxChange": 0.0,
                        "total": 0.0
                    },
                    "Partial reinsertion (CBMC)": {
                        "accepted": 0.0,
                        "all": 0,
                        "constructed": 0.0,
                        "fraction": 0.0,
                        "maxChange": 0.0,
                        "total": 0.0
                    },
                    "Random rotation": {
                        "accepted": [
                            0.0,
                            0.0,
                            0.0
                        ],
                        "all": 0,
                        "constructed": [
                            0.0,
                            0.0,
                            0.0
                        ],
                        "fraction": [
                            0.0,
                            0.0,
                            0.0
                        ],
                        "maxChange": [
                            0.0,
                            0.0,
                            0.0
                        ],
                        "total": [
                            0.0,
                            0.0,
                            0.0
                        ]
                    },
                    "Random translation": {
                        "accepted": [
                            0.0,
                            0.0,
                            0.0
                        ],
                        "all": 0,
                        "constructed": [
                            0.0,
                            0.0,
                            0.0
                        ],
                        "fraction": [
                            0.0,
                            0.0,
                            0.0
                        ],
                        "maxChange": [
                            0.0,
                            0.0,
                            0.0
                        ],
                        "total": [
                            0.0,
                            0.0,
                            0.0
                        ]
                    },
                    "Reinsertion (CBMC)": {
                        "accepted": 0.0,
                        "all": 0,
                        "constructed": 0.0,
                        "fraction": 0.0,
                        "maxChange": 0.0,
                        "total": 0.0
                    },
                    "Rotation": {
                        "accepted": [
                            0.0,
                            0.0,
                            0.0
                        ],
                        "all": 0,
                        "constructed": [
                            0.0,
                            0.0,
                            0.0
                        ],
                        "fraction": [
                            0.0,
                            0.0,
                            0.0
                        ],
                        "maxChange": [
                            1.0,
                            1.0,
                            1.0
                        ],
                        "total": [
                            0.0,
                            0.0,
                            0.0
                        ]
                    },
                    "Swap": {
                        "accepted": [
                            0.0,
                            0.0,
                            0.0
                        ],
                        "all": 0,
                        "constructed": [
                            0.0,
                            0.0,
                            0.0
                        ],
                        "fraction": [
                            0.0,
                            0.0,
                            0.0
                        ],
                        "maxChange": [
                            0.0,
                            0.0,
                            0.0
                        ],
                        "total": [
                            0.0,
                            0.0,
                            0.0
                        ]
                    },
                    "Swap (CB/CFCMC)": {
                        "accepted": [
                            0.0,
                            0.0,
                            0.0
                        ],
                        "all": 0,
                        "constructed": [
                            0.0,
                            0.0,
                            0.0
                        ],
                        "fraction": [
                            0.0,
                            0.0,
                            0.0
                        ],
                        "maxChange": [
                            0.0,
                            0.0,
                            0.5
                        ],
                        "total": [
                            0.0,
                            0.0,
                            0.0
                        ]
                    },
                    "Swap (CBMC)": {
                        "accepted": [
                            0.0,
                            0.0,
                            0.0
                        ],
                        "all": 0,
                        "constructed": [
                            0.0,
                            0.0,
                            0.0
                        ],
                        "fraction": [
                            0.0,
                            0.0,
                            0.0
                        ],
                        "maxChange": [
                            0.0,
                            0.0,
                            0.0
                        ],
                        "total": [
                            0.0,
                            0.0,
                            0.0
                        ]
                    },
                    "Swap (CFCMC)": {
                        "accepted": [
                            0.0,
                            0.0,
                            0.0
                        ],
                        "all": 0,
                        "constructed": [
                            0.0,
                            0.0,
                            0.0
                        ],
                        "fraction": [
                            0.0,
                            0.0,
                            0.0
                        ],
                        "maxChange": [
                            0.0,
                            0.0,
                            0.5
                        ],
                        "total": [
                            0.0,
                            0.0,
                            0.0
                        ]
                    },
                    "Translation": {
                        "accepted": [
                            0.0,
                            0.0,
                            0.0
                        ],
                        "all": 0,
                        "constructed": [
                            0.0,
                            0.0,
                            0.0
                        ],
                        "fraction": [
                            0.0,
                            0.0,
                            0.0
                        ],
                        "maxChange": [
                            1.0,
                            1.0,
                            1.0
                        ],
                        "total": [
                            0.0,
                            0.0,
                            0.0
                        ]
                    },
                    "Volume change": {
                        "accepted": 0.0,
                        "all": 0,
                        "constructed": 0.0,
                        "fraction": 0.0,
                        "maxChange": 0.1,
                        "total": 0.0
                    },
                    "Widom": {
                        "accepted": 0.0,
                        "all": 100000,
                        "constructed": 85166.0,
                        "fraction": 0.0,
                        "maxChange": 0.0,
                        "total": 100000.0
                    },
                    "Widom (CB/CFCMC)": {
                        "accepted": 0.0,
                        "all": 0,
                        "constructed": 0.0,
                        "fraction": 0.0,
                        "maxChange": 0.0,
                        "total": 0.0
                    },
                    "Widom (CFCMC)": {
                        "accepted": 0.0,
                        "all": 0,
                        "constructed": 0.0,
                        "fraction": 0.0,
                        "maxChange": 0.0,
                        "total": 0.0
                    }
                },
                "system": {
                    "Gibbs swap (CBMC)": {
                        "accepted": 0.0,
                        "all": 0,
                        "constructed": 0.0,
                        "fraction": 0.0,
                        "maxChange": 0.0,
                        "total": 0.0
                    },
                    "Gibbs swap (CFCMC)": {
                        "accepted": [
                            0.0,
                            0.0,
                            0.0
                        ],
                        "all": 0,
                        "constructed": [
                            0.0,
                            0.0,
                            0.0
                        ],
                        "fraction": [
                            0.0,
                            0.0,
                            0.0
                        ],
                        "maxChange": [
                            0.0,
                            0.0,
                            0.5
                        ],
                        "total": [
                            0.0,
                            0.0,
                            0.0
                        ]
                    },
                    "Gibbs volume": {
                        "accepted": 0.0,
                        "all": 0,
                        "constructed": 0.0,
                        "fraction": 0.0,
                        "maxChange": 0.1,
                        "total": 0.0
                    },
                    "Hybrid MC": {
                        "accepted": 0.0,
                        "all": 0,
                        "constructed": 0.0,
                        "fraction": 0.0,
                        "maxChange": 0.0005,
                        "total": 0.0
                    },
                    "Identity change (CBMC)": {
                        "accepted": 0.0,
                        "all": 0,
                        "constructed": 0.0,
                        "fraction": 0.0,
                        "maxChange": 0.0,
                        "total": 0.0
                    },
                    "Parallel tempering": {
                        "accepted": 0.0,
                        "all": 0,
                        "constructed": 0.0,
                        "fraction": 0.0,
                        "maxChange": 0.0,
                        "total": 0.0
                    },
                    "Partial reinsertion (CBMC)": {
                        "accepted": 0.0,
                        "all": 0,
                        "constructed": 0.0,
                        "fraction": 0.0,
                        "maxChange": 0.0,
                        "total": 0.0
                    },
                    "Random rotation": {
                        "accepted": [
                            0.0,
                            0.0,
                            0.0
                        ],
                        "all": 0,
                        "constructed": [
                            0.0,
                            0.0,
                            0.0
                        ],
                        "fraction": [
                            0.0,
                            0.0,
                            0.0
                        ],
                        "maxChange": [
                            0.0,
                            0.0,
                            0.0
                        ],
                        "total": [
                            0.0,
                            0.0,
                            0.0
                        ]
                    },
                    "Random translation": {
                        "accepted": [
                            0.0,
                            0.0,
                            0.0
                        ],
                        "all": 0,
                        "constructed": [
                            0.0,
                            0.0,
                            0.0
                        ],
                        "fraction": [
                            0.0,
                            0.0,
                            0.0
                        ],
                        "maxChange": [
                            0.0,
                            0.0,
                            0.0
                        ],
                        "total": [
                            0.0,
                            0.0,
                            0.0
                        ]
                    },
                    "Reinsertion (CBMC)": {
                        "accepted": 0.0,
                        "all": 0,
                        "constructed": 0.0,
                        "fraction": 0.0,
                        "maxChange": 0.0,
                        "total": 0.0
                    },
                    "Rotation": {
                        "accepted": [
                            0.0,
                            0.0,
                            0.0
                        ],
                        "all": 0,
                        "constructed": [
                            0.0,
                            0.0,
                            0.0
                        ],
                        "fraction": [
                            0.0,
                            0.0,
                            0.0
                        ],
                        "maxChange": [
                            1.0,
                            1.0,
                            1.0
                        ],
                        "total": [
                            0.0,
                            0.0,
                            0.0
                        ]
                    },
                    "Swap": {
                        "accepted": [
                            0.0,
                            0.0,
                            0.0
                        ],
                        "all": 0,
                        "constructed": [
                            0.0,
                            0.0,
                            0.0
                        ],
                        "fraction": [
                            0.0,
                            0.0,
                            0.0
                        ],
                        "maxChange": [
                            0.0,
                            0.0,
                            0.0
                        ],
                        "total": [
                            0.0,
                            0.0,
                            0.0
                        ]
                    },
                    "Swap (CB/CFCMC)": {
                        "accepted": [
                            0.0,
                            0.0,
                            0.0
                        ],
                        "all": 0,
                        "constructed": [
                            0.0,
                            0.0,
                            0.0
                        ],
                        "fraction": [
                            0.0,
                            0.0,
                            0.0
                        ],
                        "maxChange": [
                            0.0,
                            0.0,
                            0.5
                        ],
                        "total": [
                            0.0,
                            0.0,
                            0.0
                        ]
                    },
                    "Swap (CBMC)": {
                        "accepted": [
                            0.0,
                            0.0,
                            0.0
                        ],
                        "all": 0,
                        "constructed": [
                            0.0,
                            0.0,
                            0.0
                        ],
                        "fraction": [
                            0.0,
                            0.0,
                            0.0
                        ],
                        "maxChange": [
                            0.0,
                            0.0,
                            0.0
                        ],
                        "total": [
                            0.0,
                            0.0,
                            0.0
                        ]
                    },
                    "Swap (CFCMC)": {
                        "accepted": [
                            0.0,
                            0.0,
                            0.0
                        ],
                        "all": 0,
                        "constructed": [
                            0.0,
                            0.0,
                            0.0
                        ],
                        "fraction": [
                            0.0,
                            0.0,
                            0.0
                        ],
                        "maxChange": [
                            0.0,
                            0.0,
                            0.5
                        ],
                        "total": [
                            0.0,
                            0.0,
                            0.0
                        ]
                    },
                    "Translation": {
                        "accepted": [
                            0.0,
                            0.0,
                            0.0
                        ],
                        "all": 0,
                        "constructed": [
                            0.0,
                            0.0,
                            0.0
                        ],
                        "fraction": [
                            0.0,
                            0.0,
                            0.0
                        ],
                        "maxChange": [
                            1.0,
                            1.0,
                            1.0
                        ],
                        "total": [
                            0.0,
                            0.0,
                            0.0
                        ]
                    },
                    "Volume change": {
                        "accepted": 0.0,
                        "all": 0,
                        "constructed": 0.0,
                        "fraction": 0.0,
                        "maxChange": 0.1,
                        "total": 0.0
                    },
                    "Widom": {
                        "accepted": 0.0,
                        "all": 0,
                        "constructed": 0.0,
                        "fraction": 0.0,
                        "maxChange": 0.0,
                        "total": 0.0
                    },
                    "Widom (CB/CFCMC)": {
                        "accepted": 0.0,
                        "all": 0,
                        "constructed": 0.0,
                        "fraction": 0.0,
                        "maxChange": 0.0,
                        "total": 0.0
                    },
                    "Widom (CFCMC)": {
                        "accepted": 0.0,
                        "all": 0,
                        "constructed": 0.0,
                        "fraction": 0.0,
                        "maxChange": 0.0,
                        "total": 0.0
                    }
                }
            }
        },
        "cpuTimings": {
            "CO2": {
                "Widom": {
                    "Ewald": 1.9992294459998399,
                    "NonEwald": 54.83770090799994,
                    "Overhead": 0.028038799999595965,
                    "Tail": 0.26633444099993037,
                    "Total": 57.1313035949993
                }
            },
            "equilibration": 0.0,
            "gridCreation": 0.0,
            "initialization": 0.0,
            "production": 57.60681329800001,
            "summedSystemsAndComponents": {
                "Widom": {
                    "Ewald": 1.9992294459998399,
                    "NonEwald": 54.83770090799994,
                    "Overhead": 0.028038799999595965,
                    "Tail": 0.26633444099993037,
                    "Total": 57.1313035949993
                },
                "allSummed": 57.5615047949993,
                "energyPressureSampling": 0.38939821500000005,
                "overhead": 0.04530850300071165,
                "productionSimulationTime": 57.60681329800001,
                "propertySampling": 0.040802985000000076
            },
            "system": {
                "energyPressureSampling": 0.38939821500000005,
                "propertySampling": 0.040802985000000076
            },
            "total": 57.60681329800001
        },
        "drift": {
            "Ewald Fourier [K]": 0.0,
            "Ewald exclusion [K]": 0.0,
            "Ewald self [K]": 0.0,
            "Total potential energy [K]": 0.0,
            "Van der Waals (Tail) [K]": 0.0,
            "bend [K]": 0.0,
            "bendBend [K]": 0.0,
            "bendTorsion [K]": 0.0,
            "bond [K]": 0.0,
            "bondBend [K]": 0.0,
            "bondBond [K]": 0.0,
            "bondTorsion [K]": 0.0,
            "dU/dlambda Ewald [K]": 0.0,
            "dU/dlambda Real [K]": 0.0,
            "dU/dlambda VDW [K]": 0.0,
            "external field Real [K]": 0.0,
            "external field VDW [K]": 0.0,
            "framework-molecule Rea [K]": 0.0,
            "framework-molecule VDW [K]": 0.0,
            "improperTorsion [K]": 0.0,
            "intra Coulombic [K]": 0.0,
            "intra VDW [K]": 0.0,
            "inversionBend [K]": 0.0,
            "molecule-molecule Real [K]": 0.0,
            "molecule-molecule VDW [K]": 0.0,
            "outOfPlaneBend [K]": 0.0,
            "polarization [K]": 0.0,
            "torsion [K]": 0.0,
            "ureyBradley [K]": 0.0
        },
        "recomputedEnergies": {
            "Ewald Fourier [K]": 0.0,
            "Ewald exclusion [K]": 0.0,
            "Ewald self [K]": 0.0,
            "Total potential energy [K]": 0.0,
            "Van der Waals (Tail) [K]": 0.0,
            "bend [K]": 0.0,
            "bendBend [K]": 0.0,
            "bendTorsion [K]": 0.0,
            "bond [K]": 0.0,
            "bondBend [K]": 0.0,
            "bondBond [K]": 0.0,
            "bondTorsion [K]": 0.0,
            "dU/dlambda Ewald [K]": 0.0,
            "dU/dlambda Real [K]": 0.0,
            "dU/dlambda VDW [K]": 0.0,
            "external field Real [K]": 0.0,
            "external field VDW [K]": 0.0,
            "framework-molecule Rea [K]": 0.0,
            "framework-molecule VDW [K]": 0.0,
            "improperTorsion [K]": 0.0,
            "intra Coulombic [K]": 0.0,
            "intra VDW [K]": 0.0,
            "inversionBend [K]": 0.0,
            "molecule-molecule Real [K]": 0.0,
            "molecule-molecule VDW [K]": 0.0,
            "outOfPlaneBend [K]": 0.0,
            "polarization [K]": 0.0,
            "torsion [K]": 0.0,
            "ureyBradley [K]": 0.0
        },
        "runningEnergies": {
            "Ewald Fourier [K]": 0.0,
            "Ewald exclusion [K]": 0.0,
            "Ewald self [K]": 0.0,
            "Total potential energy [K]": 0.0,
            "Van der Waals (Tail) [K]": 0.0,
            "bend [K]": 0.0,
            "bendBend [K]": 0.0,
            "bendTorsion [K]": 0.0,
            "bond [K]": 0.0,
            "bondBend [K]": 0.0,
            "bondBond [K]": 0.0,
            "bondTorsion [K]": 0.0,
            "dU/dlambda Ewald [K]": 0.0,
            "dU/dlambda Real [K]": 0.0,
            "dU/dlambda VDW [K]": 0.0,
            "external field Real [K]": 0.0,
            "external field VDW [K]": 0.0,
            "framework-molecule Rea [K]": 0.0,
            "framework-molecule VDW [K]": 0.0,
            "improperTorsion [K]": 0.0,
            "intra Coulombic [K]": 0.0,
            "intra VDW [K]": 0.0,
            "inversionBend [K]": 0.0,
            "molecule-molecule Real [K]": 0.0,
            "molecule-molecule VDW [K]": 0.0,
            "outOfPlaneBend [K]": 0.0,
            "polarization [K]": 0.0,
            "torsion [K]": 0.0,
            "ureyBradley [K]": 0.0
        }
    },
    "properties": {
        "averageEnergies": {
            "Framework-Molecule": {
                "CO2": {
                    "coulombFourier": {
                        "block": [
                            0.0,
                            0.0,
                            0.0,
                            0.0,
                            0.0
                        ],
                        "confidence": 0.0,
                        "mean": 0.0
                    },
                    "coulombReal": {
                        "block": [
                            0.0,
                            0.0,
                            0.0,
                            0.0,
                            0.0
                        ],
                        "confidence": 0.0,
                        "mean": 0.0
                    },
                    "tailCorrection": {
                        "block": [
                            0.0,
                            0.0,
                            0.0,
                            0.0,
                            0.0
                        ],
                        "confidence": 0.0,
                        "mean": 0.0
                    },
                    "total": {
                        "block": [
                            0.0,
                            0.0,
                            0.0,
                            0.0,
                            0.0
                        ],
                        "confidence": 0.0,
                        "mean": 0.0
                    },
                    "vanDerWaals": {
                        "block": [
                            0.0,
                            0.0,
                            0.0,
                            0.0,
                            0.0
                        ],
                        "confidence": 0.0,
                        "mean": 0.0
                    }
                }
            },
            "totalEnergy": {
                "block": [
                    0.0,
                    0.0,
                    0.0,
                    0.0,
                    0.0
                ],
                "confidence": 0.0,
                "mean": 0.0
            }
        },
        "averageEnthalpy": null,
        "averagePressure": {
            "averagePressureTensor": {
                "confidence": [
                    [
                        184816.37682776037,
                        2.6626877444522343e-10,
                        2.2914631617165967e-10
                    ],
                    [
                        2.6626877444522343e-10,
                        184816.37682776037,
                        6.388229388888361e-12
                    ],
                    [
                        2.2914631617165967e-10,
                        6.388229388888361e-12,
                        184816.37682776045
                    ]
                ],
                "mean": [
                    [
                        -332815946.6001241,
                        -4.794948139235307e-07,
                        -4.126449692154747e-07
                    ],
                    [
                        -4.794948139235307e-07,
                        -332815946.6001241,
                        1.1503875617813842e-08
                    ],
                    [
                        -4.126449692154747e-07,
                        1.1503875617813842e-08,
                        -332815946.60012424
                    ]
                ]
            }
        }
    },
    "seed": 158557629,
    "version": "3.0.29"
}